prolothar_ca/__init__.py
prolothar_ca/ca/__init__.py
prolothar_ca/ca/dataset_generator/dataset_generator.py
prolothar_ca/ca/dataset_generator/double_round_robin.py
prolothar_ca/ca/dataset_generator/graph_color.py
prolothar_ca/ca/dataset_generator/metaplanning.cp311-win_amd64.pyd
prolothar_ca/ca/dataset_generator/metaplanning.cpp
prolothar_ca/ca/dataset_generator/metaplanning.pyx
prolothar_ca/ca/dataset_generator/multiple_knapsack.py
prolothar_ca/ca/dataset_generator/n_queens.py
prolothar_ca/ca/dataset_generator/pddl.py
prolothar_ca/ca/dataset_generator/pickle.py
prolothar_ca/ca/dataset_generator/random.py
prolothar_ca/ca/dataset_generator/sudoku.py
prolothar_ca/ca/dataset_logger/dataset_logger.py
prolothar_ca/ca/dataset_logger/filebased_dataset_logger.py
prolothar_ca/ca/dataset_logger/multiple_knacksack_dataset_logger.py
prolothar_ca/ca/dataset_logger/null_dataset_logger.py
prolothar_ca/ca/dataset_logger/sudoku_dataset_logger.py
prolothar_ca/ca/methods/__init__.py
prolothar_ca/ca/methods/augmention.py
prolothar_ca/ca/methods/method.py
prolothar_ca/ca/methods/mineacq.py
prolothar_ca/ca/methods/oracle.py
prolothar_ca/ca/methods/countor/__init__.py
prolothar_ca/ca/methods/countor/background_knowledge.py
prolothar_ca/ca/methods/countor/countor.py
prolothar_ca/ca/methods/countor/order.py
prolothar_ca/ca/methods/countor/utils.py
prolothar_ca/ca/methods/custom/__init__.py
prolothar_ca/ca/methods/custom/ca_items.py
prolothar_ca/ca/methods/custom/facade.py
prolothar_ca/ca/methods/custom/heterogenous_candidate.cp311-win_amd64.pyd
prolothar_ca/ca/methods/custom/heterogenous_candidate.cpp
prolothar_ca/ca/methods/custom/heterogenous_candidate.pxd
prolothar_ca/ca/methods/custom/heterogenous_candidate.pyx
prolothar_ca/ca/methods/custom/homogenous_ca.cp311-win_amd64.pyd
prolothar_ca/ca/methods/custom/homogenous_ca.cpp
prolothar_ca/ca/methods/custom/homogenous_ca.pyx
prolothar_ca/ca/methods/custom/homogenous_candidate.cp311-win_amd64.pyd
prolothar_constraint_acquisition-3.0.0.dist-info/LICENSE
prolothar_constraint_acquisition-3.0.0.dist-info/METADATA
prolothar_constraint_acquisition-3.0.0.dist-info/WHEEL
prolothar_constraint_acquisition-3.0.0.dist-info/top_level.txt
prolothar_constraint_acquisition-3.0.0.dist-info/RECORD
