Metadata-Version: 2.1
Name: prolothar-constraint-acquisition
Version: 3.0.0
Summary: algorithms for scheduling and learning scheduling constraints
Home-page: https://gitlab.dillinger.de/KI/DataScience/processmining/prolothar-constraint-acquisition
Author: Boris Wiegand
Author-email: boris.wiegand@stahl-holding-saar.de
Classifier: Programming Language :: Python :: 3
Classifier: Programming Language :: Python :: 3.11
License-File: LICENSE
Requires-Dist: xmltodict ==0.13.0
Requires-Dist: optapy ==9.37.0b0
Requires-Dist: nqueens ==1.0.4
Requires-Dist: py-sudoku ==1.0.3
Requires-Dist: methodtools ==0.4.5
Requires-Dist: python-sat ==1.8.dev3
Requires-Dist: graycode ==1.0.5
Requires-Dist: dataframe-image ==0.2.3
Requires-Dist: calendar-view ==2.4.1
